kong_pdk/__init__.py
kong_pdk/cli.py
kong_pdk/const.py
kong_pdk/exception.py
kong_pdk/kong.py
kong_pdk/listener.py
kong_pdk/logger.py
kong_pdk/module.py
kong_pdk/server.py
kong_pdk/pdk/__init__.py
kong_pdk/pdk/kong/__init__.py
kong_pdk/pdk/kong/cluster.py
kong_pdk/pdk/kong/ip.py
kong_pdk/pdk/kong/log.py
kong_pdk/pdk/kong/node.py
kong_pdk/pdk/kong/plugin.py
kong_pdk/pdk/kong/request.py
kong_pdk/pdk/kong/response.py
kong_pdk/pdk/kong/router.py
kong_pdk/pdk/kong/vault.py
kong_pdk/pdk/kong/client/__init__.py
kong_pdk/pdk/kong/client/tls.py
kong_pdk/pdk/kong/ctx/__init__.py
kong_pdk/pdk/kong/ctx/shared.py
kong_pdk/pdk/kong/enterprise_edition/__init__.py
kong_pdk/pdk/kong/enterprise_edition/jwe.py
kong_pdk/pdk/kong/nginx/__init__.py
kong_pdk/pdk/kong/nginx/shared.py
kong_pdk/pdk/kong/service/__init__.py
kong_pdk/pdk/kong/service/request.py
kong_pdk/pdk/kong/service/response.py
kong_pdk-0.36.dist-info/LICENSE
kong_pdk-0.36.dist-info/METADATA
kong_pdk-0.36.dist-info/WHEEL
kong_pdk-0.36.dist-info/entry_points.txt
kong_pdk-0.36.dist-info/top_level.txt
kong_pdk-0.36.dist-info/RECORD
