Metadata-Version: 2.1
Name: kong-pdk
Version: 0.36
Summary: Kong PDK for Python and Plugin Server
Home-page: https://github.com/Kong/kong-python-pdk
Author: Kong
License: Apache-2.0
Classifier: License :: OSI Approved :: Apache Software License
Classifier: Programming Language :: Python
Classifier: Programming Language :: Python :: 2.7
Classifier: Programming Language :: Python :: 3
Classifier: Programming Language :: Python :: 3.6
Classifier: Programming Language :: Python :: 3.7
Classifier: Programming Language :: Python :: 3.8
Classifier: Programming Language :: Python :: 3.9
Classifier: Programming Language :: Python :: Implementation :: CPython
Requires: gevent
Requires: msgpack
License-File: LICENSE
Requires-Dist: gevent
Requires-Dist: msgpack
